tohgym/__init__.py
tohgym/envs/__init__.py
tohgym/envs/toh_env.py
tohgym-0.0.8.dist-info/METADATA
tohgym-0.0.8.dist-info/WHEEL
tohgym-0.0.8.dist-info/top_level.txt
tohgym-0.0.8.dist-info/RECORD
