Metadata-Version: 2.1
Name: tohgym
Version: 0.0.8
Summary: UNKNOWN
Home-page: https://github.com/xadahiya/toh-gym
Author: Akshay Dahiya (forked by Ryan McDermott)
Author-email: UNKNOWN
License: UNKNOWN
Platform: UNKNOWN
Requires-Dist: gym
